dydantic/__init__.py
dydantic/_utils.py
dydantic/py.typed
dydantic-0.0.6.dist-info/LICENSE
dydantic-0.0.6.dist-info/METADATA
dydantic-0.0.6.dist-info/WHEEL
dydantic-0.0.6.dist-info/RECORD
