Metadata-Version: 2.1
Name: dydantic
Version: 0.0.6
Summary: Dynamically generate pydantic models from JSON schema.
License: MIT
Author: William Fu-Hinthorn
Author-email: 13333726+hinthornw@users.noreply.github.com
Requires-Python: >=3.9,<4.0
Classifier: License :: OSI Approved :: MIT License
Classifier: Programming Language :: Python :: 3
Classifier: Programming Language :: Python :: 3.9
Classifier: Programming Language :: Python :: 3.10
Classifier: Programming Language :: Python :: 3.11
Classifier: Programming Language :: Python :: 3.12
Provides-Extra: email
Requires-Dist: email-validator (>=2.1,<3.0) ; extra == "email"
Requires-Dist: pydantic (>=2,<3)
